Metadata-Version: 2.4
Name: trancit
Version: 1.1.0
Summary: TranCIT: Transient Causal Interaction Toolbox.
Author-email: Salar Nouri <salr.nouri@gmail.com>
Maintainer-email: Salar Nouri <salr.nouri@gmail.com>
License-Expression: BSD-2-Clause
Project-URL: Homepage, https://github.com/CMC-lab/TranCIT
Project-URL: Documentation, https://trancit.readthedocs.io
Project-URL: Repository, https://github.com/CMC-lab/TranCIT
Project-URL: Bug Tracker, https://github.com/CMC-lab/TranCIT/issues
Keywords: causality,time-series,neuroscience,statistics,causal-inference
Classifier: Development Status :: 4 - Beta
Classifier: Intended Audience :: Science/Research
Classifier: Operating System :: OS Independent
Classifier: Programming Language :: Python :: 3
Classifier: Programming Language :: Python :: 3.9
Classifier: Programming Language :: Python :: 3.10
Classifier: Programming Language :: Python :: 3.11
Classifier: Programming Language :: Python :: 3.12
Classifier: Programming Language :: Python :: 3.13
Classifier: Topic :: Scientific/Engineering :: Information Analysis
Classifier: Topic :: Scientific/Engineering :: Mathematics
Requires-Python: >=3.9
License-File: LICENSE
Requires-Dist: numpy>=1.19.5
Requires-Dist: scipy>=1.7.0
Requires-Dist: matplotlib>=3.5.0
Requires-Dist: scikit-learn>=1.0.0
Provides-Extra: dev
Requires-Dist: pytest>=7.0; extra == "dev"
Requires-Dist: pytest-cov>=4.0; extra == "dev"
Requires-Dist: flake8>=6.0; extra == "dev"
Requires-Dist: black>=23.0; extra == "dev"
Requires-Dist: mypy>=1.0; extra == "dev"
Requires-Dist: pre-commit>=3.0; extra == "dev"
Provides-Extra: docs
Requires-Dist: sphinx>=6.0; extra == "docs"
Requires-Dist: sphinx_rtd_theme>=1.0; extra == "docs"
Requires-Dist: sphinx-sitemap>=2.0; extra == "docs"
Requires-Dist: myst-parser>=1.0; extra == "docs"
Provides-Extra: test
Requires-Dist: pytest>=7.0; extra == "test"
Requires-Dist: pytest-cov>=4.0; extra == "test"
Dynamic: license-file
